zenbt/__init__.py
zenbt/multi_backtest.py
zenbt/zbt.abi3.so
zenbt/data/__init__.py
zenbt/data/btc_small.parquet
zenbt/data/data.py
zenbt/grafana/__init__.py
zenbt/grafana/dashboard.json
zenbt/grafana/dashboard.py
zenbt/grafana/echarts.js
zenbt/grafana/token_manager.py
zenbt/sdk/__init__.py
zenbt/sdk/base.py
zenbt/sdk/create_session.py
zenbt/sdk/logger.py
zenbt/sdk/order_record.py
zenbt/sdk/plotter.py
zenbt/sdk/stats.py
zenbt/sdk/tearsheet.py
zenbt/sdk/trade_record.py
zenbt/strategies/__init__.py
zenbt/strategies/ma_cross.py
zenbt-0.47.0.dist-info/METADATA
zenbt-0.47.0.dist-info/WHEEL
zenbt-0.47.0.dist-info/entry_points.txt
zenbt-0.47.0.dist-info/licenses/LICENSE.md
zenbt-0.47.0.dist-info/RECORD
