Metadata-Version: 2.3
Name: zenbt
Version: 0.47.0
Summary: Add your description here
Author-email: Alpha Zen <alpha@example.com>
License: MIT
Requires-Python: >=3.9
Requires-Dist: humanize>=4.11.0
Requires-Dist: numba>=0.60.0
Requires-Dist: numpy<2
Requires-Dist: pandas==2.2.2
Requires-Dist: polars>=1.9.0
Requires-Dist: pyarrow>=17.0.0
Requires-Dist: pydantic>=2.8.2
Requires-Dist: pyobjc-core>=10.1; sys_platform == 'darwin'
Requires-Dist: python-xlib>=0.33; sys_platform == 'linux'
Requires-Dist: pywin32>=306; sys_platform == 'win32'
Requires-Dist: quantstats==0.0.60
Requires-Dist: rich>=13.9.2
Requires-Dist: ta-lib>=0.6.0
Requires-Dist: tqdm>=4.66.5
Requires-Dist: tradingtoolbox>=0.44.0
